tools_config/__init__.py
tools_config/async_index.py
tools_config/constants.py
tools_config/index.py
tools_config/server_configuration.py
tools_config/session_provider.py
tools_config/mongo/__init__.py
tools_config/mongo/mongo_utils.py
tools_config/settings/__init__.py
tools_config/settings/settings.py
tools_config/tests/__init__.py
tools_config/tests/classification_server_config_test.py
tools_config/tests/internal_server_config_test.py
tools_config/tests/mongo_server_config_test.py
tools_config/tests/test_async_indexing.py
tools_config/tests/test_indexing.py
tools_config/tests/test_settings.py
tools_config/tests/test_vertical_config.py
tools_config/vertical/__init__.py
tools_config/vertical/vertical_config.py
tools_config/vertical/vertical_config_store.py
tools_config/vertical/script/__init__.py
tools_config/vertical/script/vertical_config.py
tools_config-0.0.2.dist-info/METADATA
tools_config-0.0.2.dist-info/WHEEL
tools_config-0.0.2.dist-info/top_level.txt
tools_config-0.0.2.dist-info/RECORD
