Metadata-Version: 2.1
Name: tools-config
Version: 0.0.2
Summary: tools_config component of pipelib
Home-page: https://github.com/teesign/pipelib
Author: 
Author-email: 
Classifier: Programming Language :: Python :: 3
Classifier: Operating System :: OS Independent
Requires-Python: >=3.6
Requires-Dist: mongomock ==3.20.0
Requires-Dist: mongoengine ==0.24.0
Requires-Dist: pyyaml ==6.0.1
Requires-Dist: tools-fs ==0.0.1
Requires-Dist: tools-commons ==0.0.1
